absor/absorbancecalculator.py
absor/dataset.py
absor/datasetabsorbancecalculator.py
absor/filtersample.py
absor/run.py
absor/setup.cfg
absor/toolkit.py
absor/__pycache__/absorbancecalculator.cpython-311.pyc
absor/__pycache__/dataset.cpython-311.pyc
absor/__pycache__/datasetabsorbancecalculator.cpython-311.pyc
absor/__pycache__/filtersample.cpython-311.pyc
absor/__pycache__/toolkit.cpython-311.pyc
absor/absor.egg-info/PKG-INFO
absor/absor.egg-info/SOURCES.txt
absor/absor.egg-info/dependency_links.txt
absor/absor.egg-info/requires.txt
absor/absor.egg-info/top_level.txt
blancapre/alphaminimizer.py
blancapre/compoundpreprocessor.py
blancapre/datasetfromfile.py
blancapre/diagnose.py
blancapre/filtersample.py
blancapre/preprocessor.py
blancapre/toolkit.py
blancapre/__pycache__/alphaminimizer.cpython-311.pyc
blancapre/__pycache__/compoundpreprocessor.cpython-311.pyc
blancapre/__pycache__/preprocessor.cpython-311.pyc
blancapre/__pycache__/toolkit.cpython-311.pyc
mwaapre/alphaminimizer.py
mwaapre/compoundpreprocessor.py
mwaapre/dataset.py
mwaapre/datasetfromfile.py
mwaapre/filtersample.py
mwaapre/preprocessor.py
mwaapre/toolkit.py
mwaapre/__pycache__/alphaminimizer.cpython-311.pyc
mwaapre/__pycache__/compoundpreprocessor.cpython-311.pyc
mwaapre/__pycache__/preprocessor.cpython-311.pyc
mwaapre/__pycache__/toolkit.cpython-311.pyc
optsys-1.1.2.dist-info/METADATA
optsys-1.1.2.dist-info/WHEEL
optsys-1.1.2.dist-info/entry_points.txt
optsys-1.1.2.dist-info/top_level.txt
optsys-1.1.2.dist-info/RECORD
